avs/__init__.py
avs/alexa.py
avs/auth.py
avs/check.py
avs/config.py
avs/main.py
avs/interface/__init__.py
avs/interface/alerts.py
avs/interface/audio_player.py
avs/interface/notifications.py
avs/interface/playback_controller.py
avs/interface/speaker.py
avs/interface/speech_recognizer.py
avs/interface/speech_synthesizer.py
avs/interface/system.py
avs/mic/__init__.py
avs/mic/alsa_recorder.py
avs/mic/pyaudio_recorder.py
avs/player/__init__.py
avs/player/gstreamer_player.py
avs/player/mpg123_player.py
avs/player/mpv_player.py
avs/resources/README.md
avs/resources/alarm.mp3
avs/resources/web/index.html
avs-0.5.5.dist-info/LICENSE
avs-0.5.5.dist-info/METADATA
avs-0.5.5.dist-info/WHEEL
avs-0.5.5.dist-info/entry_points.txt
avs-0.5.5.dist-info/top_level.txt
avs-0.5.5.dist-info/RECORD
