Metadata-Version: 2.1
Name: avs
Version: 0.5.5
Summary: Alexa Voice Service Python SDK
Home-page: https://github.com/respeaker/avs
Author: Yihui Xiong
Author-email: yihui.xiong@hotmail.com
License: GNU General Public License v3
Keywords: alexa voice service
Platform: UNKNOWN
Classifier: Development Status :: 2 - Pre-Alpha
Classifier: Intended Audience :: Developers
Classifier: License :: OSI Approved :: GNU General Public License v3 (GPLv3)
Classifier: Natural Language :: English
Classifier: Programming Language :: Python :: 2
Classifier: Programming Language :: Python :: 2.7
Classifier: Programming Language :: Python :: 3
Classifier: Programming Language :: Python :: 3.4
Classifier: Programming Language :: Python :: 3.5
Requires-Dist: click
Requires-Dist: hyper
Requires-Dist: tornado (==5.1.1)
Requires-Dist: requests
Requires-Dist: python-dateutil
